clicycle/__init__.py
clicycle/clicycle.py
clicycle/py.typed
clicycle/theme.py
clicycle/components/__init__.py
clicycle/components/base.py
clicycle/components/code.py
clicycle/components/header.py
clicycle/components/multi_progress.py
clicycle/components/progress.py
clicycle/components/prompt.py
clicycle/components/section.py
clicycle/components/spinner.py
clicycle/components/table.py
clicycle/components/text.py
clicycle/interactive/base.py
clicycle/interactive/multi_select.py
clicycle/interactive/select.py
clicycle/modifiers/__init__.py
clicycle/modifiers/group.py
clicycle/rendering/__init__.py
clicycle/rendering/stream.py
clicycle-3.2.3.dist-info/METADATA
clicycle-3.2.3.dist-info/WHEEL
clicycle-3.2.3.dist-info/licenses/LICENSE
clicycle-3.2.3.dist-info/RECORD
