Metadata-Version: 2.4
Name: clicycle
Version: 3.2.3
Summary: A Python CLI framework built on Click, with self-spacing components and Rich theming
Project-URL: Homepage, https://github.com/Living-Content/clicycle
Project-URL: Repository, https://github.com/Living-Content/clicycle
Project-URL: Issues, https://github.com/Living-Content/clicycle/issues
Author-email: Living Content <hello@livingcontent.co>
License-Expression: MIT
License-File: LICENSE
Classifier: Development Status :: 5 - Production/Stable
Classifier: Intended Audience :: Developers
Classifier: License :: OSI Approved :: MIT License
Classifier: Programming Language :: Python :: 3
Classifier: Programming Language :: Python :: 3.11
Classifier: Programming Language :: Python :: 3.12
Requires-Python: >=3.11
Requires-Dist: click>=8.2.1
Requires-Dist: rich>=14.1.0
Provides-Extra: dev
Requires-Dist: build; extra == 'dev'
Requires-Dist: mypy>=1.17.0; extra == 'dev'
Requires-Dist: pytest-cov>=6.0.0; extra == 'dev'
Requires-Dist: pytest>=8.4.1; extra == 'dev'
Requires-Dist: ruff>=0.12.4; extra == 'dev'
Requires-Dist: twine; extra == 'dev'
Requires-Dist: types-click>=7.1.8; extra == 'dev'
